messente/__init__.py
messente/verigator/__init__.py
messente/verigator/api.py
messente/verigator/client.py
messente/verigator/controllers.py
messente/verigator/exceptions.py
messente/verigator/models.py
messente/verigator/routes.py
verigator-1.0.2.dist-info/DESCRIPTION.rst
verigator-1.0.2.dist-info/METADATA
verigator-1.0.2.dist-info/RECORD
verigator-1.0.2.dist-info/WHEEL
verigator-1.0.2.dist-info/metadata.json
verigator-1.0.2.dist-info/top_level.txt
