Metadata-Version: 2.0
Name: verigator
Version: 1.0.2
Summary: Official Verigator.com API library
Home-page: http://messente.com/documentation/
Author: Verigator.com
Author-email: admin@verigator.com
License: Apache License, Version 2
Keywords: verigator messente sms verification 2FA pin code
Platform: UNKNOWN
Requires-Dist: requests (==2.18.4)
